coimbra/__init__.py
coimbra/_version.py
coimbra/exceptions.py
tests/__init__.py
tests/conftest.py
tests/integration/__init__.py
tests/integration/test_examples.py
tests/unit/__init__.py
tests/unit/test_init.py
coimbra-0.1.0.dist-info/LICENSE
coimbra-0.1.0.dist-info/METADATA
coimbra-0.1.0.dist-info/WHEEL
coimbra-0.1.0.dist-info/top_level.txt
coimbra-0.1.0.dist-info/RECORD
